myconverter/__init__.py
myconverter/cmtom.py
myconverter/mtocm.py
local_math_library-0.1.0.dist-info/METADATA
local_math_library-0.1.0.dist-info/WHEEL
local_math_library-0.1.0.dist-info/top_level.txt
local_math_library-0.1.0.dist-info/RECORD
